starkinfra/__init__.py
starkinfra/brcodepreview/__brcodepreview.py
starkinfra/brcodepreview/__init__.py
starkinfra/cardmethod/__cardmethod.py
starkinfra/cardmethod/__init__.py
starkinfra/creditholmes/__creditholmes.py
starkinfra/creditholmes/__init__.py
starkinfra/creditholmes/log/__init__.py
starkinfra/creditholmes/log/__log.py
starkinfra/creditnote/__creditnote.py
starkinfra/creditnote/__init__.py
starkinfra/creditnote/__transfer.py
starkinfra/creditnote/invoice/__description.py
starkinfra/creditnote/invoice/__discount.py
starkinfra/creditnote/invoice/__init__.py
starkinfra/creditnote/invoice/__invoice.py
starkinfra/creditnote/log/__init__.py
starkinfra/creditnote/log/__log.py
starkinfra/creditpreview/__creditnotepreview.py
starkinfra/creditpreview/__creditpreview.py
starkinfra/creditpreview/__init__.py
starkinfra/creditsigner/__creditsigner.py
starkinfra/creditsigner/__init__.py
starkinfra/dynamicbrcode/__dynamicbrcode.py
starkinfra/dynamicbrcode/__init__.py
starkinfra/event/__event.py
starkinfra/event/__init__.py
starkinfra/event/attempt/__attempt.py
starkinfra/event/attempt/__init__.py
starkinfra/individualdocument/__individualdocument.py
starkinfra/individualdocument/__init__.py
starkinfra/individualdocument/log/__init__.py
starkinfra/individualdocument/log/__log.py
starkinfra/individualidentity/__individualidentity.py
starkinfra/individualidentity/__init__.py
starkinfra/individualidentity/log/__init__.py
starkinfra/individualidentity/log/__log.py
starkinfra/issuingbalance/__init__.py
starkinfra/issuingbalance/__issuingbalance.py
starkinfra/issuingbillinginvoice/__init__.py
starkinfra/issuingbillinginvoice/__issuingbillinginvoice.py
starkinfra/issuingbillingtransaction/__init__.py
starkinfra/issuingbillingtransaction/__issuingbillingtransaction.py
starkinfra/issuingcard/__init__.py
starkinfra/issuingcard/__issuingcard.py
starkinfra/issuingcard/log/__init__.py
starkinfra/issuingcard/log/__log.py
starkinfra/issuingdesign/__init__.py
starkinfra-0.23.0.dist-info/LICENSE.txt
starkinfra-0.23.0.dist-info/METADATA
starkinfra-0.23.0.dist-info/WHEEL
starkinfra-0.23.0.dist-info/top_level.txt
starkinfra-0.23.0.dist-info/RECORD
