Metadata-Version: 2.1
Name: starkinfra
Version: 0.23.0
Summary: SDK to facilitate Python integrations with Stark Infra
Home-page: https://github.com/starkinfra/sdk-python
Author: Stark Infra
Author-email: developers@starkbank.com
License: MIT License
Keywords: stark infra,starkinfra,sdk,open banking,openbanking,banking,open,stark
Platform: UNKNOWN
License-File: LICENSE.txt
Requires-Dist: starkcore >=0.1.0
